[
  {
    "image": "/images/activities/WISA2025.jpg",
    "description": "WISA 2025"
  },
  {
    "image": "/images/activities/20250910入学.jpg",
    "description": "师生合影20250910"
  },
  {
    "image": "/images/activities/2025毕业.jpg",
    "description": "2025届毕业合影"
  },
  {
    "image": "/images/activities/vldb2024.jpg",
    "description": "VLDB 2024"
  },
  {
    "image": "/images/activities/20240910入学.jpg",
    "description": "师生合影20240910"
  },
  {
    "image": "/images/activities/2024毕业.jpg",
    "description": "2024届毕业合影"
  },
  {
    "image": "/images/activities/20230910入学.jpg",
    "description": "师生合影20230910"
  },
  {
    "image": "/images/activities/NDBC2019.jpg",
    "description": "NDBC 2019"
  }
]
