[
  {
    "id": 1,
    "name": "Dr. John Smith",
    "institution": "Stanford University",
    "country": "United States",
    "city": "Stanford",
    "coordinates": [-122.17, 37.43],
    "visitPeriod": "2023.09 - 2024.03",
    "research": "Graph Neural Networks"
  },
  {
    "id": 2,
    "name": "Prof. Maria Garcia",
    "institution": "University of Cambridge",
    "country": "United Kingdom",
    "city": "Cambridge",
    "coordinates": [0.12, 52.20],
    "visitPeriod": "2023.06 - 2023.12",
    "research": "Knowledge Graphs"
  },
  {
    "id": 3,
    "name": "Dr. Hiroshi Tanaka",
    "institution": "University of Tokyo",
    "country": "Japan",
    "city": "Tokyo",
    "coordinates": [139.69, 35.68],
    "visitPeriod": "2024.01 - 2024.06",
    "research": "Graph Mining Algorithms"
  },
  {
    "id": 4,
    "name": "Prof. Anna Schmidt",
    "institution": "Technical University of Munich",
    "country": "Germany",
    "city": "Munich",
    "coordinates": [11.58, 48.14],
    "visitPeriod": "2023.04 - 2023.10",
    "research": "Large Language Models"
  },
  {
    "id": 5,
    "name": "Dr. Chen Wei",
    "institution": "Tsinghua University",
    "country": "China",
    "city": "Beijing",
    "coordinates": [116.41, 39.90],
    "visitPeriod": "2023.08 - 2024.02",
    "research": "Graph Learning"
  },
  {
    "id": 6,
    "name": "Prof. David Johnson",
    "institution": "University of Toronto",
    "country": "Canada",
    "city": "Toronto",
    "coordinates": [-79.38, 43.65],
    "visitPeriod": "2024.03 - 2024.09",
    "research": "Combinatorial Algorithms"
  },
  {
    "id": 7,
    "name": "Dr. Sofia Rodriguez",
    "institution": "ETH Zurich",
    "country": "Switzerland",
    "city": "Zurich",
    "coordinates": [8.54, 47.38],
    "visitPeriod": "2023.07 - 2024.01",
    "research": "Topological Graph Analysis"
  },
  {
    "id": 8,
    "name": "Prof. Li Wei",
    "institution": "Peking University",
    "country": "China",
    "city": "Beijing",
    "coordinates": [116.41, 39.90],
    "visitPeriod": "2023.05 - 2023.11",
    "research": "Graph Neural Networks"
  }
]